pcoupang_api/__init__.py
pcoupang_api/main.py
PCoupangAPI-0.1.dist-info/LICENSE
PCoupangAPI-0.1.dist-info/METADATA
PCoupangAPI-0.1.dist-info/WHEEL
PCoupangAPI-0.1.dist-info/top_level.txt
PCoupangAPI-0.1.dist-info/RECORD
