Metadata-Version: 2.1
Name: PCoupangAPI
Version: 0.1
Summary: A Python wrapper for the Coupang partner API
Home-page: https://github.com/JEJEMEME/PCoupangAPI
Author: raykim
Author-email: ray@jejememe.com
Keywords: coupang partner api wrapper
License-File: LICENSE
Requires-Dist: requests
